safelz4-0.1.0.dist-info/METADATA
safelz4-0.1.0.dist-info/WHEEL
safelz4-0.1.0.dist-info/entry_points.txt
safelz4-0.1.0.dist-info/licenses/LICENCE.md
safelz4.libs/libgcc_s-27e5a392.so.1
safelz4/__init__.py
safelz4/__main__.py
safelz4/_cli/__init__.py
safelz4/_cli/_entry.py
safelz4/_safelz4_rs.abi3.so
safelz4/block/__init__.py
safelz4/block/__init__.pyi
safelz4/error/__init__.py
safelz4/error/__init__.pyi
safelz4/frame/__init__.py
safelz4/frame/__init__.pyi
safelz4/py.typed
safelz4-0.1.0.dist-info/RECORD
