Metadata-Version: 2.4
Name: safelz4
Version: 0.1.0
Classifier: Programming Language :: Rust
Classifier: Programming Language :: Python :: Implementation :: CPython
Classifier: Programming Language :: Python :: Implementation :: PyPy
Classifier: Intended Audience :: Developers
Classifier: Intended Audience :: Education
Classifier: Development Status :: 5 - Production/Stable
Classifier: Operating System :: OS Independent
Classifier: Programming Language :: Python :: 3
Classifier: Programming Language :: Python :: 3.7
Classifier: Programming Language :: Python :: 3.8
Classifier: Programming Language :: Python :: 3.9
Classifier: Programming Language :: Python :: 3.10
Classifier: Topic :: System :: Archiving :: Compression
Classifier: Typing :: Typed
Requires-Dist: black==22.3 ; extra == 'quality'
Requires-Dist: click==8.0.4 ; extra == 'quality'
Requires-Dist: isort>=5.5.4 ; extra == 'quality'
Requires-Dist: flake8>=3.8.3 ; extra == 'quality'
Requires-Dist: setuptools-rust>=1.5.2 ; extra == 'testing'
Requires-Dist: pytest>=7.2.0 ; extra == 'testing'
Requires-Dist: pytest-benchmark>=4.0.0 ; extra == 'testing'
Requires-Dist: hypothesis>=6.70.2 ; extra == 'testing'
Requires-Dist: xxhash ; extra == 'testing'
Requires-Dist: safelz4[testing] ; extra == 'fuzzing'
Requires-Dist: atheris>=2.3.0 ; extra == 'fuzzing'
Provides-Extra: quality
Provides-Extra: testing
Provides-Extra: fuzzing
License-File: LICENCE.md
Summary: safe LZ4 data compress library.
Author-email: Luca Vivona <lucavivona01@gmail.com>
Requires-Python: >=3.8
